.travis.yml
README.md
pypackage.mk
requirements.txt
setup.json
setup.py
docs/.gitignore
docs/docs.mk
docs/dummy.py
docs/epydoc.cfg
docs/gitadd.zsh
docs/sphinxtogithub.py.old
docs/source/.gitignore
docs/source/INSTALL.md
docs/source/README.rst
docs/source/TODO.txt
docs/source/building_docs.rst
docs/source/changelog.rst
docs/source/commandline.rst
docs/source/commands.rst
docs/source/commands_list.html
docs/source/conf.py
docs/source/config.rst
docs/source/config_list.html
docs/source/definitions.txt
docs/source/developer.rst
docs/source/developer_db.rst
docs/source/developer_packages.rst
docs/source/download.html
docs/source/events.rst
docs/source/extending.rst
docs/source/features.rst
docs/source/graph.rst
docs/source/index-fork.html
docs/source/index-logo.html
docs/source/index.rst
docs/source/initial_picture.key
docs/source/install.rst.old
docs/source/limitations.rst
docs/source/parallel.rst
docs/source/priorities.rst
docs/source/related.rst
docs/source/tutorial.key
docs/source/tutorial_basic.rst
docs/source/tutorial_cluster.rst.old
docs/source/tutorial_console.rst
docs/source/tutorial_embedding.rst
docs/source/tutorial_parmake.rst
docs/source/twitter_badge.html
docs/source/why.rst
docs/source/workers.jpg
docs/source/my_static/.gitignore
docs/source/my_static/2015-compmake-v3.png
docs/source/my_static/initial.png
docs/source/my_static/algos/compmake_1.py
docs/source/my_static/algos/compmake_jobs_deps.py
docs/source/my_static/algos/compmake_jobs_dynamic.py
docs/source/my_static/algos/compmake_jobs_returning.py
docs/source/my_static/demos/example.py
docs/source/my_static/demos/example_fail.py
docs/source/my_static/example1/.gitignore
docs/source/my_static/example1/create_pictures.sh
docs/source/my_static/example1/graph3
docs/source/my_static/example1/graph3.png
docs/source/my_static/example1/graph_after
docs/source/my_static/example1/graph_after.png
docs/source/my_static/example1/graph_after_compact
docs/source/my_static/example1/graph_after_compact.png
src/compmake_z6.egg-info/PKG-INFO
src/compmake_z6.egg-info/SOURCES.txt
src/compmake_z6.egg-info/dependency_links.txt
src/compmake_z6.egg-info/entry_points.txt
src/compmake_z6.egg-info/requires.txt
src/compmake_z6.egg-info/top_level.txt